{
  "meta": {
    "week": "week 1",
    "duration": "04-06-Sun-04-12-Sat",
    "season": "2025 Spring",
    "ep_range": "ep.1-2"
  },
  "entries": [
    {
      "rank": 2,
      "trend": "new",
      "title": "LAZARUS",
      "jpTitle": "ラザロ",
      "kv": "lazarus",
      "episode": 1,
      "genre": [
        "Action",
        "Sci-Fi"
      ],
      "wrp_score": 9.6,
      "score": 10,
      "review": {
        "en": "",
        "jp": "”あらゆる意味でちょっとレベルが違いすぎるし、またターゲットが明らかに前提として全世界、アニメファン世代問わず全対象的なものでリズム、音楽、アクション、構成、全ての見せ方が別次元だった。設定やテーマも非常に興味深くて第1話として申し分ないどころか実直にぶっ飛んでいて正攻法で叩きのめされた。主人公のアクション・パルクールでここまでずっとみさせられるとは・・。キャラデザ、キャラ、機械、乗り物、建物、あらゆるデザインも凄いものがあった。オリジナルだしこれから、とくに終盤や最後どうなっていくのかはわからないけど今のところは非常に楽しみ。やられたなー。”?10点"
      },
      "wrp_breakdown": {
        "base_score": 5,
        "animation": 0.8,
        "script": 0.75,
        "direction": 0.75,
        "charm": 0.65,
        "overall": 1.65
      },
      "romanized_title": "LAZARUS",
      "release_date": "4/6/2025 to 6/29/2025",
      "based_on": "Original",
      "studios": "MAPPA",
      "creators": "Shinichiro Watanabe",
      "external_scores": "7.21 (MAL)",
      "streaming_services": "",
      "synopsis": "\"The year is 2052 ? an era of unprecedented peace and prosperity prevails across the globe. The reason for this: mankind has been freed from sickness and pain. Nobel Prize winning neuroscientist Dr. Skinner has developed a miracle cure-all drug with no apparent drawbacks called Hapuna. Hapuna soon becomes ubiquitous… and essential. However, soon after Hapuna is officially introduced, Dr. Skinner vanishes."
    },
    {
      "rank": 3,
      "trend": "up",
      "title": "Once Upon a Witch's Death",
      "jpTitle": "ある魔女が死ぬまで",
      "kv": "arumajo",
      "episode": 2,
      "genre": [
        "Adventure",
        "Drama",
        "Fantasy"
      ],
      "wrp_score": 9.55,
      "score": 10,
      "review": {
        "en": "",
        "jp": "”1話目厳しくしすぎたかもだけどそれはそれでいい。またこの第2話も正直めちゃめちゃズルい。これで泣かない人いるか？ただ前半の親友？のおじいちゃんの時計の話と後半の話の繋がり、またお師匠さんとヒロインの関係と想いというもの、そして思い出の木とおばあちゃんの繋がり、全ての繋がりと描き方、演出が素晴らしかった。それでも多少の粗さというか大雑把さみたいなものを感じないわけではないが大きな想いを作品から感じることが出来るのでいいと思う。OPEDにもそれが十分に現れている気がする。第2話からしっかりとキャラや作品の魅力が出ているのも高得点の理由。今後に期待。毎回泣かされるのは勘弁してほしいけど。”－10点・CW"
      },
      "wrp_breakdown": {
        "base_score": 5,
        "animation": 0.7,
        "script": 0.75,
        "direction": 0.8,
        "charm": 0.65,
        "overall": 1.65
      },
      "romanized_title": "Aru Majo ga Shinu Made",
      "release_date": "4/1/2025",
      "based_on": "Web Novel",
      "studios": "EMT Squared",
      "creators": "Atsushi Nigorikawa",
      "external_scores": "",
      "streaming_services": "",
      "synopsis": "\"On Meg’s seventeenth birthday, she learns that she only has one year left to live. Her mentor?the Eternal Witch, Faust?explains that she is cursed and the only way to save herself is to grow a seed of life using one thousand tears of joy. Of course, such tears aren’t easy to come by. As Meg begins her quest, she finds herself drawn into the lives of her friends and neighbors in ways she never imagined. By sharing their burdens and using her magic to comfort them, she learns how precious those moments of connection can be even in the face of death.\""
    },
    {
      "rank": 4,
      "trend": "down",
      "title": "Shoshimin: How to Become Ordinary 2",
      "jpTitle": "小市民シリーズ（第2期）",
      "kv": "shoshimin",
      "episode": 11,
      "genre": [
        "Mystery",
        "School",
        "Slice of Life"
      ],
      "wrp_score": 9.5,
      "score": 10,
      "review": {
        "en": "",
        "jp": "\"こいつはとんでもない。OPEDもやばい。OPの1コマ目から持っていかれた。そして全体の構成・クオリティ、何もかもが1,2ランク上で圧倒的な才能が溢れている。1期を知らない人やこれ系、またこの雰囲気、小佐内ちゃんが好みじゃない人には全然刺さらないだろうということも承知しているがそれでも!と言いたいくらいの2期目のスタート(第11話)として間違いなく『凄い』と言えるものを見せてくれた。今までのものが確実に深く積み重なり結びつきつつそれが更にもっと厄介で怖いというのもいい。まぁ一つ一つの描写などが半端なくて最良質のドラマや映画を見ている感覚。っていうか小佐内が強すぎる。強いて言うなら新聞部部長の彼ってあんなに切れ者だったっけ?ってくらい。覚えてないんですけどね。それにしてもすげーな。ヨルシカやばいし。羊宮妃那ちゃんは薬がはまってますねぇ。ただ刺さらない人には全然刺さらないのは間違いない。せいぜい8点でしょう。ただ自分としては「薬屋」と本作は現時点で圧倒的に他の作品から抜け出ているのは間違いないということでこの今クール第1話に9点は付けられませんってことです。\""
      },
      "wrp_breakdown": {
        "base_score": 5,
        "animation": 0.75,
        "script": 0.75,
        "direction": 0.75,
        "charm": 0.6,
        "overall": 1.65
      },
      "romanized_title": "Shoushimin Series 2nd Season",
      "release_date": "4/5/2025 to 6/22/2025",
      "based_on": "Novels",
      "studios": "Lapin Track",
      "creators": "Mamoru Kanbe",
      "external_scores": "8.03 (MAL)",
      "streaming_services": "",
      "synopsis": "\"The second season will focus on two new cases from the novel series, adapting the two-part third volume Shuuki Gentei Kuri Kinton Jiken (The Autumn-Exclusive Kuri Kinton Case) and the fifth volume Touki Gentei Bonbon Chocolat Jiken (The Winter-Exclusive Chocolate Bonbons Case).\""
    },
    {
      "rank": 5,
      "trend": "new",
      "title": "Uma Musume: Cinderella Grey",
      "jpTitle": "ウマ娘 シンデレラグレイ",
      "kv": "umamusume",
      "episode": 1,
      "genre": [
        "Drama",
        "Sports"
      ],
      "wrp_score": 9.45,
      "score": 9,
      "review": {
        "en": "",
        "jp": "”比較的地味なスタートが逆に最初からやりすぎずにちゃんと積み上げていく見せ方としてすごく良かった。その中に絶妙に凄さや格の違いが垣間見えるしバックグラウンドや地方競馬の現実の中出の・・・という環境などもしっかりと描いていたのがここしばらくの派生エンタメでしかなかった「ウマ娘」フランチャイズとの違いを決定的に見せてくれていたと感じたので高得点を付けざるを得なかった。間違いなく面白いでしょう。”－９点"
      },
      "wrp_breakdown": {
        "base_score": 5,
        "animation": 0.7,
        "script": 0.75,
        "direction": 0.75,
        "charm": 0.65,
        "overall": 1.6
      },
      "romanized_title": "Uma Musume: Cinderella Gray",
      "release_date": "4/6/2025 to 6/29/2025",
      "based_on": "Media Mix",
      "studios": "Cygames Pictures",
      "creators": "Yuuki Itou",
      "external_scores": "8.47 (MAL)",
      "streaming_services": "",
      "synopsis": "\"Unbeknownst to those around her in the destitute countryside of Kasamatsu, the staggering potential of this ashen-haired \"\"Beast” will soon rock Japan with her feet and catapult her to the national stage?down the path of a legend."
    },
    {
      "rank": "spotlight",
      "trend": "down",
      "title": "Kowloon Generic Romance",
      "jpTitle": "九龍ジェネリックロマンス",
      "kv": "kowloon",
      "episode": 1,
      "genre": [
        "Mystery",
        "Drama",
        "Sice of Life",
        "Sci-Fi"
      ],
      "wrp_score": 9.3,
      "score": 9,
      "review": {
        "en": "",
        "jp": ""
      },
      "wrp_breakdown": {
        "base_score": 5,
        "animation": 0.75,
        "script": 0.7,
        "direction": 0.7,
        "charm": 0.65,
        "overall": 1.5
      },
      "romanized_title": "Kowloon Generic Romance",
      "release_date": "4/5/2025 to 6/28/2025",
      "based_on": "Manga",
      "studios": "ARVO ANIMATION",
      "creators": "yoshiaki Iwasaki",
      "external_scores": "7.47 (MAL)",
      "streaming_services": "",
      "synopsis": "\"Welcome to Kowloon Walled City: a dystopian townscape where the people are brimming with nostalgia, and where the past, present, and future converge. Amid the hidden emotions and extraordinary daily lives of the men and women working in its confines, a tale of romance begins to unfold for real estate agent Reiko Kujirai?one that feels as familiar as Kowloon itself…\""
    },
    {
      "rank": "editor's pick",
      "trend": "down",
      "title": "Sword of the Demon Hunter",
      "jpTitle": "鬼人幻燈抄",
      "kv": "kijin",
      "episode": 1,
      "genre": [
        "Action",
        "Historical",
        "Drama"
      ],
      "wrp_score": 9.4,
      "score": 9,
      "review": {
        "en": "",
        "jp": "雑な所、もっと時間をかけて描いてたら・・・と思う所、ご都合なところ、謎に誰も突っ込まないところ・・・などなどを考えるとすごく良かったので感情では10点だけど・・・って感じで9点にします。”予想外の事態、『横浜アニメーションラボ』だから2クール決定しているとはいえ「どうせ・・・・」と思っていたが初回1時間（これも知らなかった）をたっぷり使った素晴らしい出来を見せてくれた。基本2000年代を感じさせる絵柄、設定、演出、ストーリーだがいずれいしても1時間の間ずっと引き込み続ける熱さとロマンをもって描いてくれた。そりゃあ設定や展開などに多少の粗さとかあるけどそれでも・・・と思えるものを見せてくれたし、170年という時を超えてという意味もわかりその設定にも非常に興味が持てた。その期間果たしてどの様に過ごしてきて何があったのかなどもこれからじっくり見せてほしいと期待してやまない。それでもやっぱり多少の粗さと過度なアピールのための残酷さは気になるので今後もうちょっとなんとかなると良いな・・・と思う。取り敢えず嬉しい期待外れでした。”"
      },
      "wrp_breakdown": {
        "base_score": 5,
        "animation": 0.7,
        "script": 0.75,
        "direction": 0.75,
        "charm": 0.65,
        "overall": 1.55
      },
      "romanized_title": "KIJIN GENTOUSHOU",
      "release_date": "3/31/2025",
      "based_on": "Naro",
      "studios": "Yokohama Animation Laboratory",
      "creators": "Kazuya Aiura",
      "external_scores": "",
      "streaming_services": "",
      "synopsis": "\"In the Edo period, there was a shrine maiden called \"\"Itsukihime\"\" in the mountain village of Kadono. Jinta, a young man who acts as the shrine maiden's guardian despite being a stranger, encounters a mysterious demon who speaks of the far future in the forest where he went to defeat it. From Edo to the Heisei era, this huge Japanese fantasy series follows a demon man who travels through time while continuously questioning the meaning of wielding a sword.\""
    },
    {
      "rank": "dookie",
      "trend": "new",
      "title": "Summer Pockets",
      "jpTitle": "サマーポケッツ",
      "kv": "samapoke",
      "episode": 1,
      "genre": [
        "Drrama",
        "Romance",
        "Supernatural",
        "Slice of Life"
      ],
      "wrp_score": 6.4,
      "score": 6,
      "review": {
        "en": "",
        "jp": "久しぶりのKEY作品だからキープするけど相当やばい。クオリティも作画も脚本も演出も全てがやばくて意味不明だしテンポ悪いし魅力ないし外してるし。スロウスタートだと信じて様子見ます。ナンノコッチャ？"
      },
      "wrp_breakdown": {
        "base_score": 5,
        "animation": 0.5,
        "script": 0.3,
        "direction": 0.3,
        "charm": 0.2,
        "overall": -1.5
      },
      "romanized_title": "Summer Pockets",
      "release_date": "4/7/2025",
      "based_on": "Light Novel",
      "studios": "feel.",
      "creators": "Tomoki Kobayashi",
      "external_scores": "",
      "streaming_services": "",
      "synopsis": "\"Takahara Hairi never expected summer to feel like a dream. Sent to Torishirojima Island to sort through his late grandmother’s belongings, he’s met with endless sea, quiet nostalgia, and mysterious girls, each chasing something just out of reach. As he settles into island life, lost memories begin to surface and he finds what he never knew he’d lost.\""
    }
  ]
}